baka_tenshi/__init__.py
baka_tenshi/config.py
baka_tenshi/meta.py
baka_tenshi/schema.py
baka_tenshi/service.py
baka_tenshi/type.py
baka_tenshi/util.py
baka_tenshi-1.0.3.dist-info/DESCRIPTION.rst
baka_tenshi-1.0.3.dist-info/METADATA
baka_tenshi-1.0.3.dist-info/RECORD
baka_tenshi-1.0.3.dist-info/WHEEL
baka_tenshi-1.0.3.dist-info/metadata.json
baka_tenshi-1.0.3.dist-info/top_level.txt
