Metadata-Version: 2.0
Name: baka-tenshi
Version: 1.0.3
Summary: Baka: Skeleton framework built top of pyramid, baka_tenshi for sqlalchemy
Home-page: https://github.com/baka-framework/baka_tenshi
Author: Nanang Suryadi
Author-email: nanang.jobs@gmail.com
License: MIT
Download-URL: https://github.com/baka-framework/baka_tenshi/archive/1.0.0.tar.gz
Keywords: model,sqlalchemy,framework
Platform: UNKNOWN
Classifier: Development Status :: 3 - Alpha
Classifier: Environment :: Web Environment
Classifier: Framework :: Pyramid
Classifier: Intended Audience :: Developers
Classifier: Topic :: Software Development :: Libraries
Classifier: License :: OSI Approved :: MIT License
Classifier: Programming Language :: Python :: 2
Classifier: Programming Language :: Python :: 2.6
Classifier: Programming Language :: Python :: 2.7
Classifier: Programming Language :: Python :: 3
Classifier: Programming Language :: Python :: 3.2
Classifier: Programming Language :: Python :: 3.3
Classifier: Programming Language :: Python :: 3.4
Classifier: Operating System :: OS Independent
Requires-Dist: setuptools
Requires-Dist: trafaret
Requires-Dist: pyramid
Requires-Dist: sqlalchemy
Requires-Dist: zope.sqlalchemy
Requires-Dist: transaction
Requires-Dist: pyramid-retry
Requires-Dist: pyramid-tm
Requires-Dist: awesome-slugify
Requires-Dist: bcrypt
